NCBI_ID_grab/IDfind.py
NCBI_ID_grab/__init__.py
NCBI_ID_grab/__main__.py
NCBI_ID_grab/data/Local_NCBI_db.csv
NCBI_id_grab-0.1.5.dist-info/METADATA
NCBI_id_grab-0.1.5.dist-info/WHEEL
NCBI_id_grab-0.1.5.dist-info/entry_points.txt
NCBI_id_grab-0.1.5.dist-info/top_level.txt
NCBI_id_grab-0.1.5.dist-info/RECORD
